bwu/ext.py
bwu/model.py
bwu/com/syncer.py
bwu/utils/__init__.py
bwu/utils/account.py
bwu/utils/basic.py
bwu/utils/client.py
bwu/utils/ext.py
bwu/utils/file.py
bwu/utils/filemeta.py
bwu_cli/__init__.py
bwu_cli/__main__.py
bwu-0.2.1.dist-info/METADATA
bwu-0.2.1.dist-info/WHEEL
bwu-0.2.1.dist-info/entry_points.txt
bwu-0.2.1.dist-info/licenses/LICENSE
bwu-0.2.1.dist-info/RECORD
